markii/__init__.py
markii/appengine.py
markii/markii.py
markii/frameworks/__init__.py
markii/frameworks/falcon.py
markii/frameworks/webapp2.py
markii/static/markii.css
markii/static/markii.js
markii/static/template.html
markii-0.4.6.dist-info/DESCRIPTION.rst
markii-0.4.6.dist-info/METADATA
markii-0.4.6.dist-info/RECORD
markii-0.4.6.dist-info/WHEEL
markii-0.4.6.dist-info/metadata.json
markii-0.4.6.dist-info/top_level.txt
