Metadata-Version: 2.0
Name: markii
Version: 0.4.6
Summary: MarkII is a development-mode error handler for Python web applications.
Home-page: https://github.com/Bogdanp/markii
Author: Bogdan Popa
Author-email: popa.bogdanp@gmail.com
License: UNKNOWN
Keywords: web,errors,debugging
Platform: UNKNOWN
Classifier: Development Status :: 5 - Production/Stable
Classifier: Intended Audience :: Developers
Classifier: License :: OSI Approved :: MIT License
Classifier: Topic :: Software Development :: Debuggers
Requires-Dist: jinja2
Requires-Dist: six
